news_server/__init__.py
news_server/server.py
news_server-0.1.0.dist-info/licenses/LICENSE
news_server-0.1.0.dist-info/METADATA
news_server-0.1.0.dist-info/WHEEL
news_server-0.1.0.dist-info/top_level.txt
news_server-0.1.0.dist-info/RECORD
