Metadata-Version: 2.4
Name: news-server
Version: 0.1.0
Summary: A MCP server for news search and sentiment analysis
Author-email: Your Name <your.email@example.com>
Classifier: Programming Language :: Python :: 3
Classifier: License :: OSI Approved :: MIT License
Classifier: Operating System :: OS Independent
Requires-Python: >=3.8
License-File: LICENSE
Requires-Dist: fastmcp>=0.1.0
Requires-Dist: python-dotenv>=1.0.0
Requires-Dist: openai>=1.12.0
Requires-Dist: httpx>=0.27.0
Dynamic: license-file
